umbrella/__init__.py
umbrella/dump.py
umbrella/flags.py
umbrella/iterator.py
umbrella/runtime.py
umbrella/trailing_objects.py
umbrella/java/__init__.py
umbrella/java/access_flags.py
umbrella/java/attribute.py
umbrella/java/constant_pool.py
umbrella/java/file.py
umbrella/java/structs.py
umbrella/objc/__init__.py
umbrella/objc/base.py
umbrella/objc/decoder.py
umbrella/objc/dumper.py
umbrella/objc/model.py
umbrella/objc/pointer.py
umbrella/objc/structs.py
umbrella/swift/__init__.py
umbrella/swift/base.py
umbrella/swift/demangler.py
umbrella/swift/dumper.py
umbrella/swift/generic_context.py
umbrella/swift/metadata.py
umbrella/swift/metadata_values.py
umbrella/swift/model.py
umbrella/swift/records.py
umbrella/swift/relative_pointer.py
umbrella_py-0.0.3.dist-info/LICENSE
umbrella_py-0.0.3.dist-info/METADATA
umbrella_py-0.0.3.dist-info/WHEEL
umbrella_py-0.0.3.dist-info/top_level.txt
umbrella_py-0.0.3.dist-info/RECORD
