Metadata-Version: 2.1
Name: umbrella-py
Version: 0.0.3
Summary: ObjC and Swift application binary interface (ABI) to inspect static runtime information. (w. Class-Dump)
Author-email: MatrixEditor <not@supported.com>
Project-URL: Homepage, https://github.com/MatrixEditor/umbrella-py
Project-URL: API-Docs, https://matrixeditor.github.io/umbrella-py
Classifier: Development Status :: 1 - Planning
Classifier: Intended Audience :: Science/Research
Classifier: Intended Audience :: Developers
Classifier: License :: OSI Approved :: Apache Software License
Classifier: Programming Language :: Python :: 3.9
Classifier: Programming Language :: Python :: 3.10
Classifier: Programming Language :: Python :: 3.11
Classifier: Topic :: Scientific/Engineering :: Information Analysis
License-File: LICENSE
Requires-Dist: lief
Requires-Dist: construct
Requires-Dist: capstone
Requires-Dist: construct-dataclasses
Requires-Dist: pygments
